tsputil/__init__.py
tsputil/tsputil.py
tsputil-1.1.0a1.dist-info/DESCRIPTION.rst
tsputil-1.1.0a1.dist-info/METADATA
tsputil-1.1.0a1.dist-info/RECORD
tsputil-1.1.0a1.dist-info/WHEEL
tsputil-1.1.0a1.dist-info/metadata.json
tsputil-1.1.0a1.dist-info/top_level.txt
